{
  "description": "Environment is the Schema for the Environments API. Manages a Container App Environment.",
  "type": "object",
  "required": [
    "spec"
  ],
  "properties": {
    "apiVersion": {
      "description": "APIVersion defines the versioned schema of this representation of an object.\nServers should convert recognized schemas to the latest internal value, and\nmay reject unrecognized values.\nMore info: https://git.k8s.io/community/contributors/devel/sig-architecture/api-conventions.md#resources",
      "type": "string"
    },
    "kind": {
      "description": "Kind is a string value representing the REST resource this object represents.\nServers may infer this from the endpoint the client submits requests to.\nCannot be updated.\nIn CamelCase.\nMore info: https://git.k8s.io/community/contributors/devel/sig-architecture/api-conventions.md#types-kinds",
      "type": "string"
    },
    "metadata": {
      "type": "object"
    },
    "spec": {
      "description": "EnvironmentSpec defines the desired state of Environment",
      "type": "object",
      "required": [
        "forProvider"
      ],
      "properties": {
        "deletionPolicy": {
          "description": "DeletionPolicy specifies what will happen to the underlying external\nwhen this managed resource is deleted - either \"Delete\" or \"Orphan\" the\nexternal resource.\nThis field is planned to be deprecated in favor of the ManagementPolicies\nfield in a future release. Currently, both could be set independently and\nnon-default values would be honored if the feature flag is enabled.\nSee the design doc for more information: https://github.com/crossplane/crossplane/blob/499895a25d1a1a0ba1604944ef98ac7a1a71f197/design/design-doc-observe-only-resources.md?plain=1#L223",
          "type": "string",
          "default": "Delete",
          "enum": [
            "Orphan",
            "Delete"
          ]
        },
        "forProvider": {
          "type": "object",
          "properties": {
            "daprApplicationInsightsConnectionStringSecretRef": {
              "description": "Application Insights connection string used by Dapr to export Service to Service communication telemetry. Changing this forces a new resource to be created.\nApplication Insights connection string used by Dapr to export Service to Service communication telemetry.",
              "type": "object",
              "required": [
                "key",
                "name",
                "namespace"
              ],
              "properties": {
                "key": {
                  "description": "The key to select.",
                  "type": "string"
                },
                "name": {
                  "description": "Name of the secret.",
                  "type": "string"
                },
                "namespace": {
                  "description": "Namespace of the secret.",
                  "type": "string"
                }
              },
              "additionalProperties": false
            },
            "identity": {
              "description": "An identity block as defined below.",
              "type": "object",
              "properties": {
                "identityIds": {
                  "description": "- A list of one or more Resource IDs for User Assigned Managed identities to assign. Required when type is set to UserAssigned or SystemAssigned, UserAssigned.",
                  "type": "array",
                  "items": {
                    "type": "string"
                  },
                  "x-kubernetes-list-type": "set"
                },
                "type": {
                  "description": "The type of managed identity to assign. Possible values are SystemAssigned, UserAssigned, and SystemAssigned, UserAssigned (to enable both).",
                  "type": "string"
                }
              },
              "additionalProperties": false
            },
            "infrastructureResourceGroupName": {
              "description": "Name of the platform-managed resource group created for the Managed Environment to host infrastructure resources. Changing this forces a new resource to be created.\nName of the platform-managed resource group created for the Managed Environment to host infrastructure resources. **Note:** Only valid if a `workload_profile` is specified. If `infrastructure_subnet_id` is specified, this resource group will be created in the same subscription as `infrastructure_subnet_id`.",
              "type": "string"
            },
            "infrastructureResourceGroupNameRef": {
              "description": "Reference to a ResourceGroup in azure to populate infrastructureResourceGroupName.",
              "type": "object",
              "required": [
                "name"
              ],
              "properties": {
                "name": {
                  "description": "Name of the referenced object.",
                  "type": "string"
                },
                "policy": {
                  "description": "Policies for referencing.",
                  "type": "object",
                  "properties": {
                    "resolution": {
                      "description": "Resolution specifies whether resolution of this reference is required.\nThe default is 'Required', which means the reconcile will fail if the\nreference cannot be resolved. 'Optional' means this reference will be\na no-op if it cannot be resolved.",
                      "type": "string",
                      "default": "Required",
                      "enum": [
                        "Required",
                        "Optional"
                      ]
                    },
                    "resolve": {
                      "description": "Resolve specifies when this reference should be resolved. The default\nis 'IfNotPresent', which will attempt to resolve the reference only when\nthe corresponding field is not present. Use 'Always' to resolve the\nreference on every reconcile.",
                      "type": "string",
                      "enum": [
                        "Always",
                        "IfNotPresent"
                      ]
                    }
                  },
                  "additionalProperties": false
                }
              },
              "additionalProperties": false
            },
            "infrastructureResourceGroupNameSelector": {
              "description": "Selector for a ResourceGroup in azure to populate infrastructureResourceGroupName.",
              "type": "object",
              "properties": {
                "matchControllerRef": {
                  "description": "MatchControllerRef ensures an object with the same controller reference\nas the selecting object is selected.",
                  "type": "boolean"
                },
                "matchLabels": {
                  "description": "MatchLabels ensures an object with matching labels is selected.",
                  "type": "object",
                  "additionalProperties": {
                    "type": "string"
                  }
                },
                "policy": {
                  "description": "Policies for selection.",
                  "type": "object",
                  "properties": {
                    "resolution": {
                      "description": "Resolution specifies whether resolution of this reference is required.\nThe default is 'Required', which means the reconcile will fail if the\nreference cannot be resolved. 'Optional' means this reference will be\na no-op if it cannot be resolved.",
                      "type": "string",
                      "default": "Required",
                      "enum": [
                        "Required",
                        "Optional"
                      ]
                    },
                    "resolve": {
                      "description": "Resolve specifies when this reference should be resolved. The default\nis 'IfNotPresent', which will attempt to resolve the reference only when\nthe corresponding field is not present. Use 'Always' to resolve the\nreference on every reconcile.",
                      "type": "string",
                      "enum": [
                        "Always",
                        "IfNotPresent"
                      ]
                    }
                  },
                  "additionalProperties": false
                }
              },
              "additionalProperties": false
            },
            "infrastructureSubnetId": {
              "description": "The existing Subnet to use for the Container Apps Control Plane. Changing this forces a new resource to be created.\nThe existing Subnet to use for the Container Apps Control Plane. **NOTE:** The Subnet must have a `/21` or larger address space.",
              "type": "string"
            },
            "infrastructureSubnetIdRef": {
              "description": "Reference to a Subnet in network to populate infrastructureSubnetId.",
              "type": "object",
              "required": [
                "name"
              ],
              "properties": {
                "name": {
                  "description": "Name of the referenced object.",
                  "type": "string"
                },
                "policy": {
                  "description": "Policies for referencing.",
                  "type": "object",
                  "properties": {
                    "resolution": {
                      "description": "Resolution specifies whether resolution of this reference is required.\nThe default is 'Required', which means the reconcile will fail if the\nreference cannot be resolved. 'Optional' means this reference will be\na no-op if it cannot be resolved.",
                      "type": "string",
                      "default": "Required",
                      "enum": [
                        "Required",
                        "Optional"
                      ]
                    },
                    "resolve": {
                      "description": "Resolve specifies when this reference should be resolved. The default\nis 'IfNotPresent', which will attempt to resolve the reference only when\nthe corresponding field is not present. Use 'Always' to resolve the\nreference on every reconcile.",
                      "type": "string",
                      "enum": [
                        "Always",
                        "IfNotPresent"
                      ]
                    }
                  },
                  "additionalProperties": false
                }
              },
              "additionalProperties": false
            },
            "infrastructureSubnetIdSelector": {
              "description": "Selector for a Subnet in network to populate infrastructureSubnetId.",
              "type": "object",
              "properties": {
                "matchControllerRef": {
                  "description": "MatchControllerRef ensures an object with the same controller reference\nas the selecting object is selected.",
                  "type": "boolean"
                },
                "matchLabels": {
                  "description": "MatchLabels ensures an object with matching labels is selected.",
                  "type": "object",
                  "additionalProperties": {
                    "type": "string"
                  }
                },
                "policy": {
                  "description": "Policies for selection.",
                  "type": "object",
                  "properties": {
                    "resolution": {
                      "description": "Resolution specifies whether resolution of this reference is required.\nThe default is 'Required', which means the reconcile will fail if the\nreference cannot be resolved. 'Optional' means this reference will be\na no-op if it cannot be resolved.",
                      "type": "string",
                      "default": "Required",
                      "enum": [
                        "Required",
                        "Optional"
                      ]
                    },
                    "resolve": {
                      "description": "Resolve specifies when this reference should be resolved. The default\nis 'IfNotPresent', which will attempt to resolve the reference only when\nthe corresponding field is not present. Use 'Always' to resolve the\nreference on every reconcile.",
                      "type": "string",
                      "enum": [
                        "Always",
                        "IfNotPresent"
                      ]
                    }
                  },
                  "additionalProperties": false
                }
              },
              "additionalProperties": false
            },
            "internalLoadBalancerEnabled": {
              "description": "Should the Container Environment operate in Internal Load Balancing Mode? Defaults to false. Changing this forces a new resource to be created.\nShould the Container Environment operate in Internal Load Balancing Mode? Defaults to `false`. **Note:** can only be set to `true` if `infrastructure_subnet_id` is specified.",
              "type": "boolean"
            },
            "location": {
              "description": "Specifies the supported Azure location where the Container App Environment is to exist. Changing this forces a new resource to be created.",
              "type": "string"
            },
            "logAnalyticsWorkspaceId": {
              "description": "The ID for the Log Analytics Workspace to link this Container Apps Managed Environment to.\nThe ID for the Log Analytics Workspace to link this Container Apps Managed Environment to.",
              "type": "string"
            },
            "logAnalyticsWorkspaceIdRef": {
              "description": "Reference to a Workspace in operationalinsights to populate logAnalyticsWorkspaceId.",
              "type": "object",
              "required": [
                "name"
              ],
              "properties": {
                "name": {
                  "description": "Name of the referenced object.",
                  "type": "string"
                },
                "policy": {
                  "description": "Policies for referencing.",
                  "type": "object",
                  "properties": {
                    "resolution": {
                      "description": "Resolution specifies whether resolution of this reference is required.\nThe default is 'Required', which means the reconcile will fail if the\nreference cannot be resolved. 'Optional' means this reference will be\na no-op if it cannot be resolved.",
                      "type": "string",
                      "default": "Required",
                      "enum": [
                        "Required",
                        "Optional"
                      ]
                    },
                    "resolve": {
                      "description": "Resolve specifies when this reference should be resolved. The default\nis 'IfNotPresent', which will attempt to resolve the reference only when\nthe corresponding field is not present. Use 'Always' to resolve the\nreference on every reconcile.",
                      "type": "string",
                      "enum": [
                        "Always",
                        "IfNotPresent"
                      ]
                    }
                  },
                  "additionalProperties": false
                }
              },
              "additionalProperties": false
            },
            "logAnalyticsWorkspaceIdSelector": {
              "description": "Selector for a Workspace in operationalinsights to populate logAnalyticsWorkspaceId.",
              "type": "object",
              "properties": {
                "matchControllerRef": {
                  "description": "MatchControllerRef ensures an object with the same controller reference\nas the selecting object is selected.",
                  "type": "boolean"
                },
                "matchLabels": {
                  "description": "MatchLabels ensures an object with matching labels is selected.",
                  "type": "object",
                  "additionalProperties": {
                    "type": "string"
                  }
                },
                "policy": {
                  "description": "Policies for selection.",
                  "type": "object",
                  "properties": {
                    "resolution": {
                      "description": "Resolution specifies whether resolution of this reference is required.\nThe default is 'Required', which means the reconcile will fail if the\nreference cannot be resolved. 'Optional' means this reference will be\na no-op if it cannot be resolved.",
                      "type": "string",
                      "default": "Required",
                      "enum": [
                        "Required",
                        "Optional"
                      ]
                    },
                    "resolve": {
                      "description": "Resolve specifies when this reference should be resolved. The default\nis 'IfNotPresent', which will attempt to resolve the reference only when\nthe corresponding field is not present. Use 'Always' to resolve the\nreference on every reconcile.",
                      "type": "string",
                      "enum": [
                        "Always",
                        "IfNotPresent"
                      ]
                    }
                  },
                  "additionalProperties": false
                }
              },
              "additionalProperties": false
            },
            "logsDestination": {
              "description": "Where the application logs will be saved for this Container Apps Managed Environment. Possible values include log-analytics and azure-monitor. Omitting this value will result in logs being streamed only.",
              "type": "string"
            },
            "mutualTlsEnabled": {
              "description": "Should mutual transport layer security (mTLS) be enabled? Defaults to false.\nShould mutual transport layer security (mTLS) be enabled? Defaults to `false`. **Note:** This feature is in public preview. Enabling mTLS for your applications may increase response latency and reduce maximum throughput in high-load scenarios.",
              "type": "boolean"
            },
            "publicNetworkAccess": {
              "description": "The public network access setting for the Container App Environment. Possible values are Enabled and Disabled.\nThe public network access setting for the Container App Environment.",
              "type": "string"
            },
            "resourceGroupName": {
              "description": "The name of the resource group in which the Container App Environment is to be created. Changing this forces a new resource to be created.",
              "type": "string"
            },
            "resourceGroupNameRef": {
              "description": "Reference to a ResourceGroup in azure to populate resourceGroupName.",
              "type": "object",
              "required": [
                "name"
              ],
              "properties": {
                "name": {
                  "description": "Name of the referenced object.",
                  "type": "string"
                },
                "policy": {
                  "description": "Policies for referencing.",
                  "type": "object",
                  "properties": {
                    "resolution": {
                      "description": "Resolution specifies whether resolution of this reference is required.\nThe default is 'Required', which means the reconcile will fail if the\nreference cannot be resolved. 'Optional' means this reference will be\na no-op if it cannot be resolved.",
                      "type": "string",
                      "default": "Required",
                      "enum": [
                        "Required",
                        "Optional"
                      ]
                    },
                    "resolve": {
                      "description": "Resolve specifies when this reference should be resolved. The default\nis 'IfNotPresent', which will attempt to resolve the reference only when\nthe corresponding field is not present. Use 'Always' to resolve the\nreference on every reconcile.",
                      "type": "string",
                      "enum": [
                        "Always",
                        "IfNotPresent"
                      ]
                    }
                  },
                  "additionalProperties": false
                }
              },
              "additionalProperties": false
            },
            "resourceGroupNameSelector": {
              "description": "Selector for a ResourceGroup in azure to populate resourceGroupName.",
              "type": "object",
              "properties": {
                "matchControllerRef": {
                  "description": "MatchControllerRef ensures an object with the same controller reference\nas the selecting object is selected.",
                  "type": "boolean"
                },
                "matchLabels": {
                  "description": "MatchLabels ensures an object with matching labels is selected.",
                  "type": "object",
                  "additionalProperties": {
                    "type": "string"
                  }
                },
                "policy": {
                  "description": "Policies for selection.",
                  "type": "object",
                  "properties": {
                    "resolution": {
                      "description": "Resolution specifies whether resolution of this reference is required.\nThe default is 'Required', which means the reconcile will fail if the\nreference cannot be resolved. 'Optional' means this reference will be\na no-op if it cannot be resolved.",
                      "type": "string",
                      "default": "Required",
                      "enum": [
                        "Required",
                        "Optional"
                      ]
                    },
                    "resolve": {
                      "description": "Resolve specifies when this reference should be resolved. The default\nis 'IfNotPresent', which will attempt to resolve the reference only when\nthe corresponding field is not present. Use 'Always' to resolve the\nreference on every reconcile.",
                      "type": "string",
                      "enum": [
                        "Always",
                        "IfNotPresent"
                      ]
                    }
                  },
                  "additionalProperties": false
                }
              },
              "additionalProperties": false
            },
            "tags": {
              "description": "A mapping of tags to assign to the resource.",
              "type": "object",
              "additionalProperties": {
                "type": "string"
              },
              "x-kubernetes-map-type": "granular"
            },
            "workloadProfile": {
              "description": "One or more workload_profile blocks as defined below.",
              "type": "array",
              "items": {
                "type": "object",
                "properties": {
                  "maximumCount": {
                    "description": "The maximum number of instances of workload profile that can be deployed in the Container App Environment.",
                    "type": "number"
                  },
                  "minimumCount": {
                    "description": "The minimum number of instances of workload profile that can be deployed in the Container App Environment.",
                    "type": "number"
                  },
                  "name": {
                    "description": "The name of the workload profile.",
                    "type": "string"
                  },
                  "workloadProfileType": {
                    "description": "Workload profile type for the workloads to run on. Possible values include Consumption, D4, D8, D16, D32, E4, E8, E16 and E32.",
                    "type": "string"
                  }
                },
                "additionalProperties": false
              }
            },
            "zoneRedundancyEnabled": {
              "description": "Should the Container App Environment be created with Zone Redundancy enabled? Defaults to false. Changing this forces a new resource to be created.",
              "type": "boolean"
            }
          },
          "additionalProperties": false
        },
        "initProvider": {
          "description": "THIS IS A BETA FIELD. It will be honored\nunless the Management Policies feature flag is disabled.\nInitProvider holds the same fields as ForProvider, with the exception\nof Identifier and other resource reference fields. The fields that are\nin InitProvider are merged into ForProvider when the resource is created.\nThe same fields are also added to the terraform ignore_changes hook, to\navoid updating them after creation. This is useful for fields that are\nrequired on creation, but we do not desire to update them after creation,\nfor example because of an external controller is managing them, like an\nautoscaler.",
          "type": "object",
          "properties": {
            "daprApplicationInsightsConnectionStringSecretRef": {
              "description": "Application Insights connection string used by Dapr to export Service to Service communication telemetry. Changing this forces a new resource to be created.\nApplication Insights connection string used by Dapr to export Service to Service communication telemetry.",
              "type": "object",
              "required": [
                "key",
                "name",
                "namespace"
              ],
              "properties": {
                "key": {
                  "description": "The key to select.",
                  "type": "string"
                },
                "name": {
                  "description": "Name of the secret.",
                  "type": "string"
                },
                "namespace": {
                  "description": "Namespace of the secret.",
                  "type": "string"
                }
              },
              "additionalProperties": false
            },
            "identity": {
              "description": "An identity block as defined below.",
              "type": "object",
              "properties": {
                "identityIds": {
                  "description": "- A list of one or more Resource IDs for User Assigned Managed identities to assign. Required when type is set to UserAssigned or SystemAssigned, UserAssigned.",
                  "type": "array",
                  "items": {
                    "type": "string"
                  },
                  "x-kubernetes-list-type": "set"
                },
                "type": {
                  "description": "The type of managed identity to assign. Possible values are SystemAssigned, UserAssigned, and SystemAssigned, UserAssigned (to enable both).",
                  "type": "string"
                }
              },
              "additionalProperties": false
            },
            "infrastructureResourceGroupName": {
              "description": "Name of the platform-managed resource group created for the Managed Environment to host infrastructure resources. Changing this forces a new resource to be created.\nName of the platform-managed resource group created for the Managed Environment to host infrastructure resources. **Note:** Only valid if a `workload_profile` is specified. If `infrastructure_subnet_id` is specified, this resource group will be created in the same subscription as `infrastructure_subnet_id`.",
              "type": "string"
            },
            "infrastructureResourceGroupNameRef": {
              "description": "Reference to a ResourceGroup in azure to populate infrastructureResourceGroupName.",
              "type": "object",
              "required": [
                "name"
              ],
              "properties": {
                "name": {
                  "description": "Name of the referenced object.",
                  "type": "string"
                },
                "policy": {
                  "description": "Policies for referencing.",
                  "type": "object",
                  "properties": {
                    "resolution": {
                      "description": "Resolution specifies whether resolution of this reference is required.\nThe default is 'Required', which means the reconcile will fail if the\nreference cannot be resolved. 'Optional' means this reference will be\na no-op if it cannot be resolved.",
                      "type": "string",
                      "default": "Required",
                      "enum": [
                        "Required",
                        "Optional"
                      ]
                    },
                    "resolve": {
                      "description": "Resolve specifies when this reference should be resolved. The default\nis 'IfNotPresent', which will attempt to resolve the reference only when\nthe corresponding field is not present. Use 'Always' to resolve the\nreference on every reconcile.",
                      "type": "string",
                      "enum": [
                        "Always",
                        "IfNotPresent"
                      ]
                    }
                  },
                  "additionalProperties": false
                }
              },
              "additionalProperties": false
            },
            "infrastructureResourceGroupNameSelector": {
              "description": "Selector for a ResourceGroup in azure to populate infrastructureResourceGroupName.",
              "type": "object",
              "properties": {
                "matchControllerRef": {
                  "description": "MatchControllerRef ensures an object with the same controller reference\nas the selecting object is selected.",
                  "type": "boolean"
                },
                "matchLabels": {
                  "description": "MatchLabels ensures an object with matching labels is selected.",
                  "type": "object",
                  "additionalProperties": {
                    "type": "string"
                  }
                },
                "policy": {
                  "description": "Policies for selection.",
                  "type": "object",
                  "properties": {
                    "resolution": {
                      "description": "Resolution specifies whether resolution of this reference is required.\nThe default is 'Required', which means the reconcile will fail if the\nreference cannot be resolved. 'Optional' means this reference will be\na no-op if it cannot be resolved.",
                      "type": "string",
                      "default": "Required",
                      "enum": [
                        "Required",
                        "Optional"
                      ]
                    },
                    "resolve": {
                      "description": "Resolve specifies when this reference should be resolved. The default\nis 'IfNotPresent', which will attempt to resolve the reference only when\nthe corresponding field is not present. Use 'Always' to resolve the\nreference on every reconcile.",
                      "type": "string",
                      "enum": [
                        "Always",
                        "IfNotPresent"
                      ]
                    }
                  },
                  "additionalProperties": false
                }
              },
              "additionalProperties": false
            },
            "infrastructureSubnetId": {
              "description": "The existing Subnet to use for the Container Apps Control Plane. Changing this forces a new resource to be created.\nThe existing Subnet to use for the Container Apps Control Plane. **NOTE:** The Subnet must have a `/21` or larger address space.",
              "type": "string"
            },
            "infrastructureSubnetIdRef": {
              "description": "Reference to a Subnet in network to populate infrastructureSubnetId.",
              "type": "object",
              "required": [
                "name"
              ],
              "properties": {
                "name": {
                  "description": "Name of the referenced object.",
                  "type": "string"
                },
                "policy": {
                  "description": "Policies for referencing.",
                  "type": "object",
                  "properties": {
                    "resolution": {
                      "description": "Resolution specifies whether resolution of this reference is required.\nThe default is 'Required', which means the reconcile will fail if the\nreference cannot be resolved. 'Optional' means this reference will be\na no-op if it cannot be resolved.",
                      "type": "string",
                      "default": "Required",
                      "enum": [
                        "Required",
                        "Optional"
                      ]
                    },
                    "resolve": {
                      "description": "Resolve specifies when this reference should be resolved. The default\nis 'IfNotPresent', which will attempt to resolve the reference only when\nthe corresponding field is not present. Use 'Always' to resolve the\nreference on every reconcile.",
                      "type": "string",
                      "enum": [
                        "Always",
                        "IfNotPresent"
                      ]
                    }
                  },
                  "additionalProperties": false
                }
              },
              "additionalProperties": false
            },
            "infrastructureSubnetIdSelector": {
              "description": "Selector for a Subnet in network to populate infrastructureSubnetId.",
              "type": "object",
              "properties": {
                "matchControllerRef": {
                  "description": "MatchControllerRef ensures an object with the same controller reference\nas the selecting object is selected.",
                  "type": "boolean"
                },
                "matchLabels": {
                  "description": "MatchLabels ensures an object with matching labels is selected.",
                  "type": "object",
                  "additionalProperties": {
                    "type": "string"
                  }
                },
                "policy": {
                  "description": "Policies for selection.",
                  "type": "object",
                  "properties": {
                    "resolution": {
                      "description": "Resolution specifies whether resolution of this reference is required.\nThe default is 'Required', which means the reconcile will fail if the\nreference cannot be resolved. 'Optional' means this reference will be\na no-op if it cannot be resolved.",
                      "type": "string",
                      "default": "Required",
                      "enum": [
                        "Required",
                        "Optional"
                      ]
                    },
                    "resolve": {
                      "description": "Resolve specifies when this reference should be resolved. The default\nis 'IfNotPresent', which will attempt to resolve the reference only when\nthe corresponding field is not present. Use 'Always' to resolve the\nreference on every reconcile.",
                      "type": "string",
                      "enum": [
                        "Always",
                        "IfNotPresent"
                      ]
                    }
                  },
                  "additionalProperties": false
                }
              },
              "additionalProperties": false
            },
            "internalLoadBalancerEnabled": {
              "description": "Should the Container Environment operate in Internal Load Balancing Mode? Defaults to false. Changing this forces a new resource to be created.\nShould the Container Environment operate in Internal Load Balancing Mode? Defaults to `false`. **Note:** can only be set to `true` if `infrastructure_subnet_id` is specified.",
              "type": "boolean"
            },
            "location": {
              "description": "Specifies the supported Azure location where the Container App Environment is to exist. Changing this forces a new resource to be created.",
              "type": "string"
            },
            "logAnalyticsWorkspaceId": {
              "description": "The ID for the Log Analytics Workspace to link this Container Apps Managed Environment to.\nThe ID for the Log Analytics Workspace to link this Container Apps Managed Environment to.",
              "type": "string"
            },
            "logAnalyticsWorkspaceIdRef": {
              "description": "Reference to a Workspace in operationalinsights to populate logAnalyticsWorkspaceId.",
              "type": "object",
              "required": [
                "name"
              ],
              "properties": {
                "name": {
                  "description": "Name of the referenced object.",
                  "type": "string"
                },
                "policy": {
                  "description": "Policies for referencing.",
                  "type": "object",
                  "properties": {
                    "resolution": {
                      "description": "Resolution specifies whether resolution of this reference is required.\nThe default is 'Required', which means the reconcile will fail if the\nreference cannot be resolved. 'Optional' means this reference will be\na no-op if it cannot be resolved.",
                      "type": "string",
                      "default": "Required",
                      "enum": [
                        "Required",
                        "Optional"
                      ]
                    },
                    "resolve": {
                      "description": "Resolve specifies when this reference should be resolved. The default\nis 'IfNotPresent', which will attempt to resolve the reference only when\nthe corresponding field is not present. Use 'Always' to resolve the\nreference on every reconcile.",
                      "type": "string",
                      "enum": [
                        "Always",
                        "IfNotPresent"
                      ]
                    }
                  },
                  "additionalProperties": false
                }
              },
              "additionalProperties": false
            },
            "logAnalyticsWorkspaceIdSelector": {
              "description": "Selector for a Workspace in operationalinsights to populate logAnalyticsWorkspaceId.",
              "type": "object",
              "properties": {
                "matchControllerRef": {
                  "description": "MatchControllerRef ensures an object with the same controller reference\nas the selecting object is selected.",
                  "type": "boolean"
                },
                "matchLabels": {
                  "description": "MatchLabels ensures an object with matching labels is selected.",
                  "type": "object",
                  "additionalProperties": {
                    "type": "string"
                  }
                },
                "policy": {
                  "description": "Policies for selection.",
                  "type": "object",
                  "properties": {
                    "resolution": {
                      "description": "Resolution specifies whether resolution of this reference is required.\nThe default is 'Required', which means the reconcile will fail if the\nreference cannot be resolved. 'Optional' means this reference will be\na no-op if it cannot be resolved.",
                      "type": "string",
                      "default": "Required",
                      "enum": [
                        "Required",
                        "Optional"
                      ]
                    },
                    "resolve": {
                      "description": "Resolve specifies when this reference should be resolved. The default\nis 'IfNotPresent', which will attempt to resolve the reference only when\nthe corresponding field is not present. Use 'Always' to resolve the\nreference on every reconcile.",
                      "type": "string",
                      "enum": [
                        "Always",
                        "IfNotPresent"
                      ]
                    }
                  },
                  "additionalProperties": false
                }
              },
              "additionalProperties": false
            },
            "logsDestination": {
              "description": "Where the application logs will be saved for this Container Apps Managed Environment. Possible values include log-analytics and azure-monitor. Omitting this value will result in logs being streamed only.",
              "type": "string"
            },
            "mutualTlsEnabled": {
              "description": "Should mutual transport layer security (mTLS) be enabled? Defaults to false.\nShould mutual transport layer security (mTLS) be enabled? Defaults to `false`. **Note:** This feature is in public preview. Enabling mTLS for your applications may increase response latency and reduce maximum throughput in high-load scenarios.",
              "type": "boolean"
            },
            "publicNetworkAccess": {
              "description": "The public network access setting for the Container App Environment. Possible values are Enabled and Disabled.\nThe public network access setting for the Container App Environment.",
              "type": "string"
            },
            "tags": {
              "description": "A mapping of tags to assign to the resource.",
              "type": "object",
              "additionalProperties": {
                "type": "string"
              },
              "x-kubernetes-map-type": "granular"
            },
            "workloadProfile": {
              "description": "One or more workload_profile blocks as defined below.",
              "type": "array",
              "items": {
                "type": "object",
                "properties": {
                  "maximumCount": {
                    "description": "The maximum number of instances of workload profile that can be deployed in the Container App Environment.",
                    "type": "number"
                  },
                  "minimumCount": {
                    "description": "The minimum number of instances of workload profile that can be deployed in the Container App Environment.",
                    "type": "number"
                  },
                  "name": {
                    "description": "The name of the workload profile.",
                    "type": "string"
                  },
                  "workloadProfileType": {
                    "description": "Workload profile type for the workloads to run on. Possible values include Consumption, D4, D8, D16, D32, E4, E8, E16 and E32.",
                    "type": "string"
                  }
                },
                "additionalProperties": false
              }
            },
            "zoneRedundancyEnabled": {
              "description": "Should the Container App Environment be created with Zone Redundancy enabled? Defaults to false. Changing this forces a new resource to be created.",
              "type": "boolean"
            }
          },
          "additionalProperties": false
        },
        "managementPolicies": {
          "description": "THIS IS A BETA FIELD. It is on by default but can be opted out\nthrough a Crossplane feature flag.\nManagementPolicies specify the array of actions Crossplane is allowed to\ntake on the managed and external resources.\nThis field is planned to replace the DeletionPolicy field in a future\nrelease. Currently, both could be set independently and non-default\nvalues would be honored if the feature flag is enabled. If both are\ncustom, the DeletionPolicy field will be ignored.\nSee the design doc for more information: https://github.com/crossplane/crossplane/blob/499895a25d1a1a0ba1604944ef98ac7a1a71f197/design/design-doc-observe-only-resources.md?plain=1#L223\nand this one: https://github.com/crossplane/crossplane/blob/444267e84783136daa93568b364a5f01228cacbe/design/one-pager-ignore-changes.md",
          "type": "array",
          "default": [
            "*"
          ],
          "items": {
            "description": "A ManagementAction represents an action that the Crossplane controllers\ncan take on an external resource.",
            "type": "string",
            "enum": [
              "Observe",
              "Create",
              "Update",
              "Delete",
              "LateInitialize",
              "*"
            ]
          }
        },
        "providerConfigRef": {
          "description": "ProviderConfigReference specifies how the provider that will be used to\ncreate, observe, update, and delete this managed resource should be\nconfigured.",
          "type": "object",
          "default": {
            "name": "default"
          },
          "required": [
            "name"
          ],
          "properties": {
            "name": {
              "description": "Name of the referenced object.",
              "type": "string"
            },
            "policy": {
              "description": "Policies for referencing.",
              "type": "object",
              "properties": {
                "resolution": {
                  "description": "Resolution specifies whether resolution of this reference is required.\nThe default is 'Required', which means the reconcile will fail if the\nreference cannot be resolved. 'Optional' means this reference will be\na no-op if it cannot be resolved.",
                  "type": "string",
                  "default": "Required",
                  "enum": [
                    "Required",
                    "Optional"
                  ]
                },
                "resolve": {
                  "description": "Resolve specifies when this reference should be resolved. The default\nis 'IfNotPresent', which will attempt to resolve the reference only when\nthe corresponding field is not present. Use 'Always' to resolve the\nreference on every reconcile.",
                  "type": "string",
                  "enum": [
                    "Always",
                    "IfNotPresent"
                  ]
                }
              },
              "additionalProperties": false
            }
          },
          "additionalProperties": false
        },
        "writeConnectionSecretToRef": {
          "description": "WriteConnectionSecretToReference specifies the namespace and name of a\nSecret to which any connection details for this managed resource should\nbe written. Connection details frequently include the endpoint, username,\nand password required to connect to the managed resource.",
          "type": "object",
          "required": [
            "name",
            "namespace"
          ],
          "properties": {
            "name": {
              "description": "Name of the secret.",
              "type": "string"
            },
            "namespace": {
              "description": "Namespace of the secret.",
              "type": "string"
            }
          },
          "additionalProperties": false
        }
      },
      "additionalProperties": false,
      "x-kubernetes-validations": [
        {
          "rule": "!('*' in self.managementPolicies || 'Create' in self.managementPolicies || 'Update' in self.managementPolicies) || has(self.forProvider.location) || (has(self.initProvider) \u0026\u0026 has(self.initProvider.location))",
          "message": "spec.forProvider.location is a required parameter"
        }
      ]
    },
    "status": {
      "description": "EnvironmentStatus defines the observed state of Environment.",
      "type": "object",
      "properties": {
        "atProvider": {
          "type": "object",
          "properties": {
            "customDomainVerificationId": {
              "description": "The ID of the Custom Domain Verification for this Container App Environment.\nThe ID of the Custom Domain Verification for this Container App Environment.",
              "type": "string"
            },
            "defaultDomain": {
              "description": "The default, publicly resolvable, name of this Container App Environment.\nThe default publicly resolvable name of this Container App Environment",
              "type": "string"
            },
            "dockerBridgeCidr": {
              "description": "The network addressing in which the Container Apps in this Container App Environment will reside in CIDR notation.\nThe network addressing in which the Container Apps in this Container App Environment will reside in CIDR notation.",
              "type": "string"
            },
            "id": {
              "description": "The ID of the Container App Environment",
              "type": "string"
            },
            "identity": {
              "description": "An identity block as defined below.",
              "type": "object",
              "properties": {
                "identityIds": {
                  "description": "- A list of one or more Resource IDs for User Assigned Managed identities to assign. Required when type is set to UserAssigned or SystemAssigned, UserAssigned.",
                  "type": "array",
                  "items": {
                    "type": "string"
                  },
                  "x-kubernetes-list-type": "set"
                },
                "principalId": {
                  "description": "The ID of the Container App Environment",
                  "type": "string"
                },
                "tenantId": {
                  "description": "The ID of the Container App Environment",
                  "type": "string"
                },
                "type": {
                  "description": "The type of managed identity to assign. Possible values are SystemAssigned, UserAssigned, and SystemAssigned, UserAssigned (to enable both).",
                  "type": "string"
                }
              },
              "additionalProperties": false
            },
            "infrastructureResourceGroupName": {
              "description": "Name of the platform-managed resource group created for the Managed Environment to host infrastructure resources. Changing this forces a new resource to be created.\nName of the platform-managed resource group created for the Managed Environment to host infrastructure resources. **Note:** Only valid if a `workload_profile` is specified. If `infrastructure_subnet_id` is specified, this resource group will be created in the same subscription as `infrastructure_subnet_id`.",
              "type": "string"
            },
            "infrastructureSubnetId": {
              "description": "The existing Subnet to use for the Container Apps Control Plane. Changing this forces a new resource to be created.\nThe existing Subnet to use for the Container Apps Control Plane. **NOTE:** The Subnet must have a `/21` or larger address space.",
              "type": "string"
            },
            "internalLoadBalancerEnabled": {
              "description": "Should the Container Environment operate in Internal Load Balancing Mode? Defaults to false. Changing this forces a new resource to be created.\nShould the Container Environment operate in Internal Load Balancing Mode? Defaults to `false`. **Note:** can only be set to `true` if `infrastructure_subnet_id` is specified.",
              "type": "boolean"
            },
            "location": {
              "description": "Specifies the supported Azure location where the Container App Environment is to exist. Changing this forces a new resource to be created.",
              "type": "string"
            },
            "logAnalyticsWorkspaceId": {
              "description": "The ID for the Log Analytics Workspace to link this Container Apps Managed Environment to.\nThe ID for the Log Analytics Workspace to link this Container Apps Managed Environment to.",
              "type": "string"
            },
            "logsDestination": {
              "description": "Where the application logs will be saved for this Container Apps Managed Environment. Possible values include log-analytics and azure-monitor. Omitting this value will result in logs being streamed only.",
              "type": "string"
            },
            "mutualTlsEnabled": {
              "description": "Should mutual transport layer security (mTLS) be enabled? Defaults to false.\nShould mutual transport layer security (mTLS) be enabled? Defaults to `false`. **Note:** This feature is in public preview. Enabling mTLS for your applications may increase response latency and reduce maximum throughput in high-load scenarios.",
              "type": "boolean"
            },
            "platformReservedCidr": {
              "description": "The IP range, in CIDR notation, that is reserved for environment infrastructure IP addresses.\nThe IP range, in CIDR notation, that is reserved for environment infrastructure IP addresses.",
              "type": "string"
            },
            "platformReservedDnsIpAddress": {
              "description": "The IP address from the IP range defined by platform_reserved_cidr that is reserved for the internal DNS server.\nThe IP address from the IP range defined by `platform_reserved_cidr` that is reserved for the internal DNS server.",
              "type": "string"
            },
            "publicNetworkAccess": {
              "description": "The public network access setting for the Container App Environment. Possible values are Enabled and Disabled.\nThe public network access setting for the Container App Environment.",
              "type": "string"
            },
            "resourceGroupName": {
              "description": "The name of the resource group in which the Container App Environment is to be created. Changing this forces a new resource to be created.",
              "type": "string"
            },
            "staticIpAddress": {
              "description": "The Static IP address of the Environment.\nThe Static IP Address of the Environment.",
              "type": "string"
            },
            "tags": {
              "description": "A mapping of tags to assign to the resource.",
              "type": "object",
              "additionalProperties": {
                "type": "string"
              },
              "x-kubernetes-map-type": "granular"
            },
            "workloadProfile": {
              "description": "One or more workload_profile blocks as defined below.",
              "type": "array",
              "items": {
                "type": "object",
                "properties": {
                  "maximumCount": {
                    "description": "The maximum number of instances of workload profile that can be deployed in the Container App Environment.",
                    "type": "number"
                  },
                  "minimumCount": {
                    "description": "The minimum number of instances of workload profile that can be deployed in the Container App Environment.",
                    "type": "number"
                  },
                  "name": {
                    "description": "The name of the workload profile.",
                    "type": "string"
                  },
                  "workloadProfileType": {
                    "description": "Workload profile type for the workloads to run on. Possible values include Consumption, D4, D8, D16, D32, E4, E8, E16 and E32.",
                    "type": "string"
                  }
                },
                "additionalProperties": false
              }
            },
            "zoneRedundancyEnabled": {
              "description": "Should the Container App Environment be created with Zone Redundancy enabled? Defaults to false. Changing this forces a new resource to be created.",
              "type": "boolean"
            }
          },
          "additionalProperties": false
        },
        "conditions": {
          "description": "Conditions of the resource.",
          "type": "array",
          "items": {
            "description": "A Condition that may apply to a resource.",
            "type": "object",
            "required": [
              "lastTransitionTime",
              "reason",
              "status",
              "type"
            ],
            "properties": {
              "lastTransitionTime": {
                "description": "LastTransitionTime is the last time this condition transitioned from one\nstatus to another.",
                "type": "string",
                "format": "date-time"
              },
              "message": {
                "description": "A Message containing details about this condition's last transition from\none status to another, if any.",
                "type": "string"
              },
              "observedGeneration": {
                "description": "ObservedGeneration represents the .metadata.generation that the condition was set based upon.\nFor instance, if .metadata.generation is currently 12, but the .status.conditions[x].observedGeneration is 9, the condition is out of date\nwith respect to the current state of the instance.",
                "type": "integer",
                "format": "int64"
              },
              "reason": {
                "description": "A Reason for this condition's last transition from one status to another.",
                "type": "string"
              },
              "status": {
                "description": "Status of this condition; is it currently True, False, or Unknown?",
                "type": "string"
              },
              "type": {
                "description": "Type of this condition. At most one of each condition type may apply to\na resource at any point in time.",
                "type": "string"
              }
            },
            "additionalProperties": false
          },
          "x-kubernetes-list-map-keys": [
            "type"
          ],
          "x-kubernetes-list-type": "map"
        },
        "observedGeneration": {
          "description": "ObservedGeneration is the latest metadata.generation\nwhich resulted in either a ready state, or stalled due to error\nit can not recover from without human intervention.",
          "type": "integer",
          "format": "int64"
        }
      },
      "additionalProperties": false
    }
  }
}
